metricfarmer/__init__.py
metricfarmer/exceptions.py
metricfarmer/farmer.py
metricfarmer/helpers.py
metricfarmer/extensions/__init__.py
metricfarmer/extensions/extension.py
metricfarmer/extensions/mf/__init__.py
metricfarmer/extensions/mf/mf_extension.py
metricfarmer/extensions/mf/sources/__init__.py
metricfarmer/extensions/mf/sources/file_count.py
metricfarmer/extensions/mf/sources/random.py
metricfarmer/extensions/mf/sources/rest.py
metricfarmer/extensions/mf/sources/static.py
metricfarmer/extensions/mf/targets/__init__.py
metricfarmer/extensions/mf/targets/db_sqlite.py
metricfarmer/extensions/mf/targets/file_csv.py
metricfarmer/extensions/mf/targets/file_json.py
metricfarmer/extensions/mf/targets/file_text.py
metricfarmer/extensions/mf/targets/print_json.py
metricfarmer/extensions/mf/targets/print_text.py
metricfarmer-0.2.0.dist-info/LICENSE
metricfarmer-0.2.0.dist-info/METADATA
metricfarmer-0.2.0.dist-info/WHEEL
metricfarmer-0.2.0.dist-info/entry_points.txt
metricfarmer-0.2.0.dist-info/top_level.txt
metricfarmer-0.2.0.dist-info/RECORD
