Metadata-Version: 2.1
Name: metricfarmer
Version: 0.2.0
Summary: Collects and stores metrics for your project.
Home-page: http://github.com/useblocks/metricfarmer
Author: team useblocks
Author-email: info@useblocks.com
License: MIT
Download-URL: http://pypi.python.org/pypi/metricfarmer
Platform: any
Classifier: Development Status :: 5 - Production/Stable
Classifier: Intended Audience :: Developers
Classifier: License :: OSI Approved :: MIT License
Classifier: Operating System :: OS Independent
Classifier: Programming Language :: Python
Classifier: Programming Language :: Python :: 3
Classifier: Programming Language :: Python :: 3.5
Classifier: Programming Language :: Python :: 3.6
Classifier: Programming Language :: Python :: 3.7
Classifier: Topic :: Documentation
Classifier: Topic :: Utilities
Requires-Dist: click
Requires-Dist: colorama
Requires-Dist: requests
